{
  "properties": {
    "connectionReferences": {
      "shared_teams_1": {
        "runtimeSource": "embedded",
        "connection": {
          "connectionReferenceLogicalName": "dd_TeamsTicketDiscussionTeams"
        },
        "api": { "name": "shared_teams" }
      },
      "shared_commondataserviceforapps": {
        "runtimeSource": "embedded",
        "connection": {
          "connectionReferenceLogicalName": "dd_TeamsTicketDiscussionDataverse"
        },
        "api": { "name": "shared_commondataserviceforapps" }
      },
      "shared_deskdirector_1": {
        "runtimeSource": "embedded",
        "connection": {
          "connectionReferenceLogicalName": "dd_TeamsTicketDiscussionDeskDirector"
        },
        "api": { "name": "shared_deskdirector" }
      }
    },
    "definition": {
      "$schema": "https://schema.management.azure.com/providers/Microsoft.Logic/schemas/2016-06-01/workflowdefinition.json#",
      "contentVersion": "1.0.0.0",
      "parameters": {
        "$connections": { "defaultValue": {}, "type": "Object" },
        "$authentication": { "defaultValue": {}, "type": "SecureObject" }
      },
      "triggers": {
        "When_a_ticket_is_created_or_updated": {
          "metadata": {
            "operationMetadataId": "c9e75403-3fcd-40fd-9bc5-532384d49edd"
          },
          "type": "OpenApiConnectionWebhook",
          "inputs": {
            "host": {
              "connectionName": "shared_deskdirector_1",
              "operationId": "CreateTicketWorkflow",
              "apiId": "/providers/Microsoft.PowerApps/apis/shared_deskdirector"
            },
            "parameters": {
              "type": "ticket.tags.updated",
              "req/description": "Teams Ticket Discussion - Ticket Tagged",
              "req/advancedFilters/newTags": ["teams"]
            },
            "authentication": "@parameters('$authentication')"
          },
          "description": "Ticket is tagged with 'teams'"
        }
      },
      "actions": {
        "DeskDirector_Domain": {
          "runAfter": { "Get_Config": ["Succeeded"] },
          "metadata": {
            "operationMetadataId": "64d4c8e9-8650-4194-afe2-58653550a5ef"
          },
          "type": "ParseJson",
          "inputs": {
            "content": { "domain": "@body('Parse_Config')?['ddDomain']" },
            "schema": {
              "type": "object",
              "properties": { "domain": { "type": "string" } }
            }
          }
        },
        "Post_message_in_a_chat_or_channel": {
          "runAfter": { "Ticket_Hyperlink": ["Succeeded"] },
          "metadata": {
            "operationMetadataId": "90fae727-eb15-44db-87e4-070b9fe4677c"
          },
          "type": "OpenApiConnection",
          "inputs": {
            "host": {
              "connectionName": "shared_teams_1",
              "operationId": "PostMessageToConversation",
              "apiId": "/providers/Microsoft.PowerApps/apis/shared_teams"
            },
            "parameters": {
              "poster": "@body('Parse_Config')?['postAs']",
              "location": "@body('Parse_Config')?['postIn']",
              "body": {
                "recipient": {
                  "groupId": "@body('Parse_Config')?['groupId']",
                  "channelId": "@body('Parse_Config')?['channelId']"
                },
                "messageBody": "<span style='font-size:20px'><b>@{triggerOutputs()?['body/ticket/name']}</b></span><br><p>Contact: @{triggerOutputs()?['body/ticket/contact/name']} (@{triggerOutputs()?['body/ticket/contact/emailAddress']})<br>@{outputs('Ticket_Hyperlink')}</p>"
              }
            },
            "authentication": "@parameters('$authentication')"
          }
        },
        "Ticket_Hyperlink": {
          "runAfter": { "DeskDirector_Domain": ["Succeeded"] },
          "metadata": {
            "operationMetadataId": "c9e0fabf-d00b-4c09-95cb-4f342cb271cf"
          },
          "type": "Compose",
          "inputs": "<a href=\"https://@{body('DeskDirector_Domain')?['domain']}/tech/tickets/@{triggerOutputs()?['body/ticket/id']}/details\">View in Tech</a>"
        },
        "Update_a_ticket": {
          "runAfter": { "Add_or_update_row": ["Succeeded"] },
          "metadata": {
            "operationMetadataId": "c2eeb366-3e38-4f76-a628-2344ef78fb55"
          },
          "type": "OpenApiConnection",
          "inputs": {
            "host": {
              "connectionName": "shared_deskdirector_1",
              "operationId": "UpdateTicket",
              "apiId": "/providers/Microsoft.PowerApps/apis/shared_deskdirector"
            },
            "parameters": {
              "ticketId": "@triggerOutputs()?['body/ticket/id']",
              "req/noteContent": "[A Teams discussion was started here](@{outputs('Post_message_in_a_chat_or_channel')?['body/messageLink']})",
              "req/noteIsInternal": true
            },
            "authentication": "@parameters('$authentication')"
          }
        },
        "Get_Config": {
          "actions": {
            "List_Config": {
              "runAfter": {},
              "metadata": {
                "operationMetadataId": "f49b4e3e-fe6d-4f5e-b42f-e53525b2370e"
              },
              "type": "OpenApiConnection",
              "inputs": {
                "host": {
                  "connectionName": "shared_commondataserviceforapps",
                  "operationId": "ListRecords",
                  "apiId": "/providers/Microsoft.PowerApps/apis/shared_commondataserviceforapps"
                },
                "parameters": {
                  "entityName": "dd_teamsticketdiscussionconfigs",
                  "$select": "dd_configid, dd_deskdirectordomain, dd_teamspostin, dd_teamspostas, dd_teamsteamid, dd_teamschannelid",
                  "$filter": "dd_configid eq '0'"
                },
                "authentication": "@parameters('$authentication')"
              }
            },
            "Only_one_config_entry": {
              "actions": {
                "Parse_Config": {
                  "runAfter": {},
                  "metadata": {
                    "operationMetadataId": "f8b6a009-01eb-48ef-8475-9a86b9da811c"
                  },
                  "type": "ParseJson",
                  "inputs": {
                    "content": {
                      "ddDomain": "@outputs('List_Config')?['body/value'][0]['dd_deskdirectordomain']",
                      "postAs": "@outputs('List_Config')?['body/value'][0]['dd_teamspostas']",
                      "postIn": "@outputs('List_Config')?['body/value'][0]['dd_teamspostin']",
                      "channelId": "@outputs('List_Config')?['body/value'][0]['dd_teamschannelid']",
                      "groupId": "@outputs('List_Config')?['body/value'][0]['dd_teamsteamid']"
                    },
                    "schema": {
                      "type": "object",
                      "properties": {
                        "ddDomain": { "type": "string" },
                        "postAs": { "type": "string" },
                        "postIn": { "type": "string" },
                        "channelId": { "type": "string" },
                        "groupId": { "type": "string" }
                      }
                    }
                  }
                }
              },
              "runAfter": { "List_Config": ["Succeeded"] },
              "else": {
                "actions": {
                  "Terminate_-_Conflicting_Config": {
                    "runAfter": {},
                    "metadata": {
                      "operationMetadataId": "fb3fc2e2-a252-4500-af14-83b14038a1f7"
                    },
                    "type": "Terminate",
                    "inputs": { "runStatus": "Cancelled" }
                  }
                }
              },
              "expression": {
                "equals": ["@length(outputs('List_Config')?['body/value'])", 1]
              },
              "metadata": {
                "operationMetadataId": "7ddc5078-af0f-4d3c-9877-a1a10e000535"
              },
              "type": "If"
            }
          },
          "runAfter": {},
          "metadata": {
            "operationMetadataId": "53d38b50-49bf-4816-ba96-2a10c1339657"
          },
          "type": "Scope"
        },
        "List_rows": {
          "runAfter": { "Post_message_in_a_chat_or_channel": ["Succeeded"] },
          "metadata": {
            "operationMetadataId": "350df07c-e8ff-420f-9e99-ce304b8856aa"
          },
          "type": "OpenApiConnection",
          "inputs": {
            "host": {
              "connectionName": "shared_commondataserviceforapps",
              "operationId": "ListRecords",
              "apiId": "/providers/Microsoft.PowerApps/apis/shared_commondataserviceforapps"
            },
            "parameters": {
              "entityName": "dd_teamsticketdiscussionstates",
              "$select": "dd_teamsticketdiscussionstateid, dd_ticketid, dd_teamsmessageid",
              "$filter": "dd_ticketid eq '@{triggerOutputs()?['body/ticket/id']}'"
            },
            "authentication": "@parameters('$authentication')"
          }
        },
        "Add_or_update_row": {
          "actions": {
            "Add_a_new_row": {
              "runAfter": {},
              "metadata": {
                "operationMetadataId": "64d09613-4115-4e09-9b8a-003eab7e93ea"
              },
              "type": "OpenApiConnection",
              "inputs": {
                "host": {
                  "connectionName": "shared_commondataserviceforapps",
                  "operationId": "CreateRecord",
                  "apiId": "/providers/Microsoft.PowerApps/apis/shared_commondataserviceforapps"
                },
                "parameters": {
                  "entityName": "dd_teamsticketdiscussionstates",
                  "item/dd_teamsmessageid": "@outputs('Post_message_in_a_chat_or_channel')?['body/id']",
                  "item/dd_ticketid": "@triggerOutputs()?['body/ticket/id']"
                },
                "authentication": "@parameters('$authentication')"
              }
            }
          },
          "runAfter": { "List_rows": ["Succeeded"] },
          "else": {
            "actions": {
              "Update_a_row": {
                "runAfter": {},
                "metadata": {
                  "operationMetadataId": "6f74e35c-7fb2-41d4-8f3f-67d9fd43b4a3"
                },
                "type": "OpenApiConnection",
                "inputs": {
                  "host": {
                    "connectionName": "shared_commondataserviceforapps",
                    "operationId": "UpdateRecord",
                    "apiId": "/providers/Microsoft.PowerApps/apis/shared_commondataserviceforapps"
                  },
                  "parameters": {
                    "entityName": "dd_teamsticketdiscussionstates",
                    "recordId": "@ outputs('List_rows')?['body/value'][0]?['dd_teamsticketdiscussionstateid']",
                    "item/dd_teamsmessageid": "@outputs('Post_message_in_a_chat_or_channel')?['body/id']"
                  },
                  "authentication": "@parameters('$authentication')"
                },
                "description": "Update the row with new teams thread id"
              }
            }
          },
          "expression": {
            "equals": ["@length(outputs('List_rows')?['body/value'])", 0]
          },
          "metadata": {
            "operationMetadataId": "e6145e99-331b-46e7-9ba7-61a8c8e649b3"
          },
          "type": "If"
        }
      },
      "outputs": {}
    }
  },
  "schemaVersion": "1.0.0.0"
}
